README.rst
setup.py
remtorch/__init__.py
remtorch/remote.py
remtorch.egg-info/PKG-INFO
remtorch.egg-info/SOURCES.txt
remtorch.egg-info/dependency_links.txt
remtorch.egg-info/requires.txt
remtorch.egg-info/top_level.txt