Metadata-Version: 2.1
Name: remtorch
Version: 0.0.1
Summary: A pytorch dataset that allows you to iterate the data that is on the remote machine without having to copy all the data.
Home-page: https://github.com/NRshka/remote-dataset
Author: ['A. Makarov']
Author-email: makarov.alxr@yandex.ru
License: MIT license
Platform: UNKNOWN
Classifier: Development Status :: 4 - Beta
Classifier: License :: OSI Approved :: MIT License
Classifier: Natural Language :: English
Classifier: Natural Language :: Russian
Classifier: Programming Language :: Python :: 3.7
Classifier: Operating System :: Microsoft :: Windows
Classifier: Operating System :: POSIX :: Linux
Requires-Python: >=3.6
